CHANGELOG.rst
LICENSE.txt
MANIFEST.in
README.rst
setup.py
sieve/__init__.py
sieve/operators.py
sieve/xml_compare.py
sieve.egg-info/PKG-INFO
sieve.egg-info/SOURCES.txt
sieve.egg-info/dependency_links.txt
sieve.egg-info/entry_points.txt
sieve.egg-info/not-zip-safe
sieve.egg-info/requires.txt
sieve.egg-info/top_level.txt
sieve/tests/__init__.py
sieve/tests/test_operators.py
sieve/tests/test_xml_compare.py